mailsafepro/__init__.py
mailsafepro/client.py
mailsafepro/exceptions.py
mailsafepro/models.py
mailsafepro/py.typed
mailsafepro/utils.py
mailsafepro_sdk-2.1.0.dist-info/licenses/LICENSE
mailsafepro_sdk-2.1.0.dist-info/METADATA
mailsafepro_sdk-2.1.0.dist-info/WHEEL
mailsafepro_sdk-2.1.0.dist-info/top_level.txt
mailsafepro_sdk-2.1.0.dist-info/RECORD
