Metadata-Version: 2.4
Name: mailsafepro-sdk
Version: 2.1.0
Summary: Official Python SDK for MailSafePro Email Validation API with comprehensive security features
Home-page: https://github.com/mailsafepro/mailsafepro-python-sdk
Author: MailSafePro Team
Author-email: MailSafePro Team <support@mailsafepro.com>
License: MIT
Project-URL: Homepage, https://mailsafepro.com
Project-URL: Documentation, https://docs.mailsafepro.com/sdk/python
Project-URL: Repository, https://github.com/mailsafepro/mailsafepro-python-sdk
Project-URL: Issues, https://github.com/mailsafepro/mailsafepro-python-sdk/issues
Project-URL: Changelog, https://github.com/mailsafepro/mailsafepro-python-sdk/blob/main/CHANGELOG.md
Keywords: email,validation,verification,smtp,dns,api,sdk,security,spam-trap,breach-detection,deliverability
Classifier: Development Status :: 5 - Production/Stable
Classifier: Intended Audience :: Developers
Classifier: License :: OSI Approved :: MIT License
Classifier: Operating System :: OS Independent
Classifier: Programming Language :: Python :: 3
Classifier: Programming Language :: Python :: 3.8
Classifier: Programming Language :: Python :: 3.9
Classifier: Programming Language :: Python :: 3.10
Classifier: Programming Language :: Python :: 3.11
Classifier: Programming Language :: Python :: 3.12
Classifier: Programming Language :: Python :: 3.13
Classifier: Topic :: Software Development :: Libraries :: Python Modules
Classifier: Topic :: Communications :: Email
Classifier: Topic :: Internet
Classifier: Topic :: Security
Classifier: Typing :: Typed
Requires-Python: >=3.8
License-File: LICENSE
Requires-Dist: httpx<1.0.0,>=0.24.0
Requires-Dist: pydantic<3.0.0,>=2.0.0
Provides-Extra: async
Requires-Dist: aiofiles>=23.0.0; extra == "async"
Provides-Extra: dev
Requires-Dist: pytest>=7.4.0; extra == "dev"
Requires-Dist: pytest-cov>=4.1.0; extra == "dev"
Requires-Dist: pytest-mock>=3.11.1; extra == "dev"
Requires-Dist: pytest-asyncio>=0.21.0; extra == "dev"
Requires-Dist: respx>=0.20.0; extra == "dev"
Requires-Dist: black>=24.3.0; extra == "dev"
Requires-Dist: ruff>=0.1.0; extra == "dev"
Requires-Dist: mypy>=1.5.0; extra == "dev"
Requires-Dist: bandit>=1.7.5; extra == "dev"
Requires-Dist: safety>=3.0.0; extra == "dev"
Requires-Dist: pre-commit>=3.5.0; extra == "dev"
Provides-Extra: all
Requires-Dist: mailsafepro-sdk[async,dev]; extra == "all"
Dynamic: author
Dynamic: home-page
Dynamic: license-file
Dynamic: requires-python
